[{"start_time":0,"end_time":16.229007,"label":"Reading"},{"start_time":17.225593,"end_time":24.163091,"note":"","label":"Observation"},{"start_time":24.511356,"end_time":45.79814,"note":"","label":"Observation"},{"start_time":46.419136,"end_time":51.720094,"note":"","label":"Reading"},{"start_time":51.752819,"end_time":68.027779,"note":"","label":"Reading"},{"start_time":68.207351,"end_time":77.473734,"note":"","label":"Reading"},{"start_time":78.218538,"end_time":89.475154,"note":"","label":"Procedure"},{"start_time":90.108199,"end_time":98.38655,"note":"","label":"Reading"},{"start_time":98.502016,"end_time":111.800014,"note":"","label":"Reading"},{"start_time":112.711966,"end_time":118.986585,"note":"","label":"Reading"},{"start_time":119.596832,"end_time":127.876303,"note":"","label":"Observation"},{"start_time":128.776327,"end_time":168.116636,"note":"","label":"Explanation"},{"start_time":168.76877,"end_time":178.031181,"note":"","label":"Observation"},{"start_time":178.44477,"end_time":181.702765,"note":"","label":"Procedure"},{"start_time":182.566636,"end_time":200.855497,"note":"","label":"Procedure"},{"start_time":201.495609,"end_time":211.756754,"note":"","label":"Procedure"},{"start_time":212.344889,"end_time":228.61819,"note":"","label":"Procedure"},{"start_time":229.54124,"end_time":247.830194,"note":"","label":"Reading"},{"start_time":247.997111,"end_time":261.385817,"note":"","label":"Observation"},{"start_time":261.647045,"end_time":275.937061,"note":"","label":"Observation"},{"start_time":276.042402,"end_time":284.482056,"note":"","label":"Procedure"},{"start_time":285.35312,"end_time":295.617182,"note":"","label":"Reading"},{"start_time":297.290027,"end_time":306.501601,"note":"","label":"Procedure"},{"start_time":307.14495,"end_time":329.428583,"note":"","label":"Explanation"},{"start_time":329.614509,"end_time":336.868539,"note":"","label":"Observation"},{"start_time":337.010809,"end_time":341.717131,"note":"","label":"Explanation"},{"start_time":341.789933,"end_time":355.055183,"note":"","label":"Procedure"},{"start_time":355.635667,"end_time":364.909339,"note":"","label":"Reading"},{"start_time":365.113274,"end_time":374.383965,"note":"","label":"Reading"},{"start_time":374.932861,"end_time":381.200893,"note":"","label":"Procedure"},{"start_time":382.08695,"end_time":391.368358,"note":"","label":"Reading"},{"start_time":391.53091,"end_time":404.790484,"note":"","label":"Reading"},{"start_time":405.427267,"end_time":412.704774,"note":"","label":"Reading"},{"start_time":413.416258,"end_time":419.678069,"note":"","label":"Reading"},{"start_time":420.465662,"end_time":435.757998,"note":"","label":"Reading"},{"start_time":436.225764,"end_time":466.529984,"note":"","label":"Procedure"},{"start_time":466.711906,"end_time":485.263643,"note":"","label":"Observation"},{"start_time":485.760291,"end_time":504.038176,"note":"","label":"Observation"},{"start_time":504.603195,"end_time":506.865815,"note":"","label":"Procedure"},{"start_time":507.776132,"end_time":514.056164,"note":"","label":"Procedure"},{"start_time":514.294141,"end_time":519.552875,"note":"","label":"Procedure"},{"start_time":520.1179,"end_time":536.380452,"note":"","label":"Reading"},{"start_time":536.662358,"end_time":546.916105,"note":"","label":"Observation"},{"start_time":547.576365,"end_time":560.856887,"note":"","label":"Procedure"},{"start_time":561.411123,"end_time":571.682551,"note":"","label":"Observation"},{"start_time":572.255938,"end_time":580.520476,"note":"","label":"Explanation"},{"start_time":580.682198,"end_time":593.961403,"note":"","label":"Reading"},{"start_time":594.092892,"end_time":601.833284,"note":"","label":"Procedure"},{"start_time":622.644056,"end_time":631.340465,"note":"","label":"Procedure"},{"start_time":631.465945,"end_time":645.762951,"note":"","label":"Observation"},{"start_time":646.512297,"end_time":651.785215,"note":"","label":"Procedure"},{"start_time":652.353736,"end_time":662.783335,"note":"","label":"Reading"},{"start_time":663.399971,"end_time":679.675593,"note":"","label":"Procedure"},{"start_time":679.699561,"end_time":699.991819,"note":"","label":"Observation"},{"start_time":700.752239,"end_time":714.020272,"note":"","label":"Reading"},{"start_time":714.862834,"end_time":722.12178,"note":"","label":"Reading"},{"start_time":722.594612,"end_time":726.860986,"note":"","label":"Procedure"},{"start_time":727.869299,"end_time":735.144453,"note":"","label":"Procedure"},{"start_time":735.659061,"end_time":746.244787,"note":"","label":"Reading"},{"start_time":746.442218,"end_time":"","note":"","label":"Procedure"}]